TAN/__init__.py
TAN_ENC-0.3.dist-info/METADATA
TAN_ENC-0.3.dist-info/WHEEL
TAN_ENC-0.3.dist-info/top_level.txt
TAN_ENC-0.3.dist-info/RECORD
