Metadata-Version: 2.1
Name: TAN-ENC
Version: 0.3
Summary: TAN ENCODERS
Author: TAN-ENC
Classifier: Programming Language :: Python :: 3
